vinca_core/card.py
vinca_core/cardlist.py
vinca_core/julianday.py
vinca_core/scheduling.py
vinca_core-0.1.0.dist-info/WHEEL
vinca_core-0.1.0.dist-info/METADATA
vinca_core-0.1.0.dist-info/RECORD
