Metadata-Version: 2.1
Name: vinca-core
Version: 0.1.0
Summary: Dependency or all vinca applications. Not a standalone repository
License: CC0
Author: Oscar Laird
Author-email: olaird25@gmail.com
Requires-Python: >=3.8,<4.0
Classifier: License :: Other/Proprietary License
Classifier: Programming Language :: Python :: 3
Classifier: Programming Language :: Python :: 3.10
Classifier: Programming Language :: Python :: 3.8
Classifier: Programming Language :: Python :: 3.9
